apitally/__init__.py
apitally/blacksheep.py
apitally/common.py
apitally/django.py
apitally/django_ninja.py
apitally/django_rest_framework.py
apitally/fastapi.py
apitally/flask.py
apitally/litestar.py
apitally/otel.py
apitally/py.typed
apitally/starlette.py
apitally/client/__init__.py
apitally/client/client_asyncio.py
apitally/client/client_base.py
apitally/client/client_threading.py
apitally/client/consumers.py
apitally/client/instance.py
apitally/client/logging.py
apitally/client/request_logging.py
apitally/client/requests.py
apitally/client/resources.py
apitally/client/sentry.py
apitally/client/server_errors.py
apitally/client/spans.py
apitally/client/validation_errors.py
apitally-0.24.0.dist-info/METADATA
apitally-0.24.0.dist-info/WHEEL
apitally-0.24.0.dist-info/licenses/LICENSE
apitally-0.24.0.dist-info/RECORD
