Metadata-Version: 2.4
Name: apitally
Version: 0.24.0
Summary: Simple API monitoring & analytics for REST APIs built with FastAPI, Flask, Django, Starlette, Litestar and BlackSheep.
Project-URL: Homepage, https://apitally.io
Project-URL: Documentation, https://docs.apitally.io
Project-URL: Repository, https://github.com/apitally/apitally-py
Author-email: Apitally <hello@apitally.io>
License: MIT License
License-File: LICENSE
Classifier: Development Status :: 5 - Production/Stable
Classifier: Environment :: Web Environment
Classifier: Framework :: Django
Classifier: Framework :: FastAPI
Classifier: Framework :: Flask
Classifier: Intended Audience :: Developers
Classifier: Intended Audience :: Information Technology
Classifier: License :: OSI Approved :: MIT License
Classifier: Programming Language :: Python
Classifier: Programming Language :: Python :: 3
Classifier: Programming Language :: Python :: 3 :: Only
Classifier: Programming Language :: Python :: 3.9
Classifier: Programming Language :: Python :: 3.10
Classifier: Programming Language :: Python :: 3.11
Classifier: Programming Language :: Python :: 3.12
Classifier: Programming Language :: Python :: 3.13
Classifier: Programming Language :: Python :: 3.14
Classifier: Topic :: Internet
Classifier: Topic :: Internet :: WWW/HTTP
Classifier: Topic :: Internet :: WWW/HTTP :: WSGI :: Middleware
Classifier: Topic :: Software Development
Classifier: Topic :: System :: Monitoring
Classifier: Typing :: Typed
Requires-Python: <4.0,>=3.9
Requires-Dist: backoff>=2.0.0
Requires-Dist: opentelemetry-sdk<2.0.0,>=1.39.1
Requires-Dist: psutil>=5.9.6
Requires-Dist: typing-extensions>=4.0.0; python_version < '3.11'
Provides-Extra: blacksheep
Requires-Dist: blacksheep>=2; extra == 'blacksheep'
Requires-Dist: httpx>=0.22.0; extra == 'blacksheep'
Provides-Extra: django-ninja
Requires-Dist: django-ninja>=1.0.0; extra == 'django-ninja'
Requires-Dist: django<5,>=2.2; (python_version < '3.10') and extra == 'django-ninja'
Requires-Dist: django>=2.2; (python_version >= '3.10') and extra == 'django-ninja'
Requires-Dist: requests>=2.26.0; extra == 'django-ninja'
Provides-Extra: django-rest-framework
Requires-Dist: django<5,>=2.2; (python_version < '3.10') and extra == 'django-rest-framework'
Requires-Dist: django>=2.2; (python_version >= '3.10') and extra == 'django-rest-framework'
Requires-Dist: djangorestframework>=3.10.0; extra == 'django-rest-framework'
Requires-Dist: inflection>=0.5.1; extra == 'django-rest-framework'
Requires-Dist: requests>=2.26.0; extra == 'django-rest-framework'
Requires-Dist: uritemplate>=3.0.0; extra == 'django-rest-framework'
Provides-Extra: fastapi
Requires-Dist: fastapi>=0.94.1; extra == 'fastapi'
Requires-Dist: httpx>=0.22.0; extra == 'fastapi'
Requires-Dist: starlette<1.0.0,>=0.26.1; extra == 'fastapi'
Provides-Extra: flask
Requires-Dist: flask>=2.0.0; extra == 'flask'
Requires-Dist: requests>=2.26.0; extra == 'flask'
Provides-Extra: litestar
Requires-Dist: httpx>=0.22.0; extra == 'litestar'
Requires-Dist: litestar>=2.4.0; extra == 'litestar'
Provides-Extra: starlette
Requires-Dist: httpx>=0.22.0; extra == 'starlette'
Requires-Dist: starlette<1.0.0,>=0.26.1; extra == 'starlette'
